firefly_messaging/__init__.py
firefly_messaging/application/__init__.py
firefly_messaging/application/container.py
firefly_messaging/application/service/__init__.py
firefly_messaging/application/service/api.py
firefly_messaging/domain/__init__.py
firefly_messaging/domain/entity/__init__.py
firefly_messaging/domain/entity/audience.py
firefly_messaging/domain/entity/audience_member.py
firefly_messaging/domain/entity/campaign.py
firefly_messaging/domain/entity/contact.py
firefly_messaging/domain/entity/tenant.py
firefly_messaging/domain/service/__init__.py
firefly_messaging/domain/service/email_service.py
firefly_messaging/domain/service/email_service_factory.py
firefly_messaging/infrastructure/__init__.py
firefly_messaging/infrastructure/service/__init__.py
firefly_messaging/infrastructure/service/abstract_email_service.py
firefly_messaging/infrastructure/service/aws_ses_client_factory.py
firefly_messaging/infrastructure/service/aws_ses_email_service.py
firefly_messaging/infrastructure/service/email_service.py
firefly_messaging/infrastructure/service/email_service_factory.py
firefly_messaging/infrastructure/service/mailchimp_client_factory.py
firefly_messaging/infrastructure/service/mailchimp_email_service.py
firefly_messaging/presentation/__init__.py
firefly_messaging-0.1.28.dist-info/METADATA
firefly_messaging-0.1.28.dist-info/WHEEL
firefly_messaging-0.1.28.dist-info/entry_points.txt
firefly_messaging-0.1.28.dist-info/top_level.txt
firefly_messaging-0.1.28.dist-info/RECORD
