Metadata-Version: 2.1
Name: firefly-messaging
Version: 0.1.28
Summary: Put project description here.
Home-page: UNKNOWN
Author: UNKNOWN
Author-email: UNKNOWN
License: UNKNOWN
Platform: UNKNOWN
Classifier: Programming Language :: Python :: 3.7
Classifier: Operating System :: OS Independent
Requires-Dist: firefly-dependency-injection (>=0.1)
Requires-Dist: firefly-framework (>=1.2.5)
Requires-Dist: firefly-aws (>=1.2.5)
Requires-Dist: mailchimp3 (>=3.0.14)
